envless/__init__.py
envless/envless.py
envless-0.2.0.dist-info/WHEEL
envless-0.2.0.dist-info/METADATA
envless-0.2.0.dist-info/RECORD
