Metadata-Version: 2.1
Name: envless
Version: 0.2.0
Summary: Declare your python dependencies inside your scripts
Home-page: https://github.com/cjfuller/envless
License: MIT
Author: Colin Fuller
Author-email: colin@cjf.io
Requires-Python: >=3.8
Classifier: License :: OSI Approved :: MIT License
Classifier: Programming Language :: Python :: 3
Classifier: Programming Language :: Python :: 3.10
Classifier: Programming Language :: Python :: 3.8
Classifier: Programming Language :: Python :: 3.9
